{
  "response": {
    "header": {
      "resultCode": "00",
      "resultMsg": "NORMAL SERVICE."
    },
    "body": {
      "items": {
        "item": {
          "cprn": 107.1,
          "hm10m": 100,
          "hm2m": 100,
          "localarea": 10,
          "obsid": 2019,
          "obsname": "평창 백석산",
          "pa": 880.8,
          "rn": 108.5,
          "tm": "2022-06-30 18:00",
          "tm10m": 18.5,
          "tm2m": 18.6,
          "ts": 20.3,
          "wd10m": 268,
          "wd10mstr": "W",
          "wd2m": 291.2,
          "wd2mstr": "WNW",
          "ws10m": 0.2,
          "ws2m": 0
        }
      },
      "numOfRows": 10,
      "pageNo": 1,
      "totalCount": 1
    }
  }
}